{
  "tasks": [
    {
      "text": "Doctor Appointment",
      "day": "2021-07-15T17:00:00.000Z",
      "reminder": true,
      "id": 1
    },
    {
      "text": "Food Shopping",
      "day": "2021-07-18T17:00:00.000Z",
      "reminder": false,
      "id": 2
    },
    {
      "text": "aezestrt",
      "day": "2021-07-14T06:50:18.841Z",
      "reminder": false,
      "id": 3
    },
    {
      "text": "awraerstset",
      "day": "2021-07-14T06:50:18.841Z",
      "reminder": true,
      "id": 4
    },
    {
      "text": "setrstrdtdrt",
      "day": "2021-07-14T06:50:18.841Z",
      "reminder": true,
      "id": 5
    }
  ]
}